{"about_banner.md":"CnY3HTWd","about_kona.md":"BM68g-fy","about_konado.md":"CME5MJPX","about_license.md":"lfWFjpkI","about_thanks.md":"BIETyhrr","chat_index.md":"DXa7p1P4","develop_code-contribute.md":"Cbca5-Wc","develop_core_bg-trans-effect.md":"BCM9nM-I","develop_core_shot-and-dialogue.md":"CYeY-q1O","develop_doc-contribute.md":"Bxm_BDZI","develop_feedback.md":"CQI-nImk","develop_roadmap.md":"Czt5S8H3","develop_translate-contribute.md":"vROQ6U5p","en_about_kona.md":"BJ95WHuy","en_about_konado.md":"CliuOdix","en_index.md":"BB1NqCfR","en_tutorial_install.md":"BhucLL48","index.md":"CSoC_HSv","konadotnet_install_konadotnet.md":"DKoCggBH","konadotnet_konadotnet_api.md":"CW6Yn5dO","script_actor-change-state.md":"COkZRAFw","script_actor-leave.md":"mrpeUHrd","script_actor-move.md":"BuHVhU7A","script_background-switch.md":"CNfTG0a3","script_branch.md":"B_GNl7AQ","script_conversation.md":"osF65tKp","script_create-actor.md":"CsHnbb3n","script_end-the-conversation.md":"Jtk1W1CJ","script_foundation.md":"DSu0kFyo","script_konado-script.md":"XYRruZRf","script_meta-data.md":"BGlj0oma","script_option-to-jump.md":"D9Jyfzea","tc_index.md":"Hvyz1m5A","tutorial_actor-coordinate-and-scaling.md":"C39MeXj7","tutorial_customize-the-dialogbox.md":"feiB_Lpw","tutorial_install.md":"CxB8oIJq","tutorial_profiles.md":"_G0_8WSu"}
